mrx9w9/__init__.py
mrx9w9/bugcrowd.py
mrx9w9-1.0.5.dist-info/METADATA
mrx9w9-1.0.5.dist-info/WHEEL
mrx9w9-1.0.5.dist-info/top_level.txt
mrx9w9-1.0.5.dist-info/RECORD
